empiricml-0.1.1.dist-info/licenses/LICENSE
empml/__init__.py
empml/base.py
empml/cv.py
empml/data.py
empml/errors.py
empml/lab.py
empml/lab_utils.py
empml/metrics.py
empml/pipeline.py
empml/transformers.py
empml/utils.py
empml/wrappers.py
empiricml-0.1.1.dist-info/METADATA
empiricml-0.1.1.dist-info/WHEEL
empiricml-0.1.1.dist-info/top_level.txt
empiricml-0.1.1.dist-info/RECORD
