Metadata-Version: 2.4
Name: EmpiricML
Version: 0.1.1
Summary: Python framework for building robust tabular machine learning models faster and easier
Author-email: Pasquale Trani <ptrani96ds@gmail.com>
Project-URL: Homepage, https://github.com/PasqualeTrani/EmpiricML
Project-URL: Bug Tracker, https://github.com/PasqualeTrani/EmpiricML/issues
Classifier: Programming Language :: Python :: 3
Classifier: License :: OSI Approved :: MIT License
Classifier: Operating System :: OS Independent
Requires-Python: >=3.11
License-File: LICENSE
Requires-Dist: numpy>=1.26.4
Requires-Dist: pandas>=2.2.2
Requires-Dist: pyarrow>=15.0.2
Requires-Dist: polars>=1.31.0
Requires-Dist: matplotlib>=3.9.0
Requires-Dist: scikit-learn>=1.7.1
Requires-Dist: lightgbm>=4.6.0
Requires-Dist: xgboost>=3.1.2
Requires-Dist: catboost>=1.2.8
Requires-Dist: skorch>=1.3.1
Dynamic: license-file
